{
 "id": "https://ns.nist.gov/sp800-53/req/SC-7.3",
 "version": "5.2.0",
 "label": "SC-7(3)",
 "lifecycle": "active",
 "title": "Access Points",
 "statements": [
  {
   "id": "smt",
   "modality": "must",
   "obligated-parties": [
    "https://ns.nist.gov/sp800-53/party/system"
   ],
   "prose": {
    "en": "Limit the number of external network connections to the system."
   }
  }
 ],
 "facets": {
  "https://ns.nist.gov/sp800-53/facet/narrative@1": {
   "guidance": [
    {
     "en": "Limiting the number of external network connections facilitates monitoring of inbound and outbound communications traffic. The Trusted Internet Connection DHS TIC initiative is an example of a federal guideline that requires limits on the number of external network connections. Limiting the number of external network connections to the system is important during transition periods from older to newer technologies (e.g., transitioning from IPv4 to IPv6 network protocols). Such transitions may require implementing the older and newer technologies simultaneously during the transition period and thus increase the number of access points to the system."
    }
   ]
  },
  "https://ns.nist.gov/sp800-53/facet/sp800-53a@1": {
   "objectives": [
    {
     "id": "sc-7.3_obj",
     "label": "SC-07(03)",
     "prose": {
      "en": "the number of external network connections to the system is limited."
     }
    }
   ],
   "methods": [
    {
     "method": "EXAMINE",
     "label": "SC-07(03)-Examine",
     "objects": [
      {
       "en": "System and communications protection policy"
      },
      {
       "en": "procedures addressing boundary protection"
      },
      {
       "en": "system design documentation"
      },
      {
       "en": "boundary protection hardware and software"
      },
      {
       "en": "system architecture and configuration documentation"
      },
      {
       "en": "system configuration settings and associated documentation"
      },
      {
       "en": "communications and network traffic monitoring logs"
      },
      {
       "en": "system audit records"
      },
      {
       "en": "system security plan"
      },
      {
       "en": "other relevant documents or records"
      }
     ]
    },
    {
     "method": "INTERVIEW",
     "label": "SC-07(03)-Interview",
     "objects": [
      {
       "en": "System/network administrators"
      },
      {
       "en": "organizational personnel with information security responsibilities"
      },
      {
       "en": "organizational personnel with boundary protection responsibilities"
      }
     ]
    },
    {
     "method": "TEST",
     "label": "SC-07(03)-Test",
     "objects": [
      {
       "en": "Mechanisms implementing boundary protection capabilities"
      },
      {
       "en": "mechanisms limiting the number of external network connections to the system"
      }
     ]
    }
   ]
  }
 },
 "relations": [
  {
   "type": "required",
   "ref": "https://ns.nist.gov/sp800-53/req/SC-7"
  }
 ]
}
