{
 "id": "https://ns.bsi.bund.de/c5/req/bcm-04-01ac",
 "version": "C5:2026",
 "label": "BCM-04-01AC",
 "lifecycle": "active",
 "title": {
  "en": "BCM-04 Additional Complement 01AC"
 },
 "statements": [
  {
   "id": "stmt",
   "modality": "unspecified",
   "obligated-parties": [
    "https://ns.bsi.bund.de/c5/party/cloud-service-provider"
   ],
   "prose": {
    "en": "In addition to the tests, exercises are also carried out which, among other things, have resulted in scenarios from security incidents that have already occurred in the past."
   }
  }
 ],
 "facets": {
  "https://ns.bsi.bund.de/c5/facet/narrative@1": {
   "guidance": [
    {
     "en": "Tests are primarily conducted at the operational level and are aimed at operational target groups. Tests include e.g.:\n\n1. Test of technical precautionary safeguards;\n2. Functional tests; and\n3. Plan review.\n\nExercises also take place on a tactical and strategic level. These include e.g.:\n\n1. Plan meeting;\n2. Personnel exercise;\n3. Command post exercise;\n4. Communication and alerting exercise;\n5. Simulation of scenarios; and\n6. Emergency or full exercise.\n\nRelevant third parties are in particular service organisations of the cloud service provider who contribute to the development or operation of the cloud service (cf. basic criteria SSO-02 and SSO-06). A cloud service customer is affected (in the sense of this criterion) if the test or excercise leads to a service downgrade outside of the level defined in the SLA or if the effectiveness of the plans can only be tested if the cloud service customer has to take action."
    }
   ]
  }
 }
}
