{
 "id": "https://ns.bsi.bund.de/c5/req/com-03-01ac",
 "version": "C5:2026",
 "label": "COM-03-01AC",
 "lifecycle": "active",
 "title": {
  "en": "COM-03 Additional Complement 01AC"
 },
 "statements": [
  {
   "id": "stmt",
   "modality": "unspecified",
   "obligated-parties": [
    "https://ns.bsi.bund.de/c5/party/cloud-service-provider"
   ],
   "prose": {
    "en": "Based on a risk assessment (cf. OIS-07) and technical feasibility, the cloud service provider decides to which extent internal audits are supplemented by procedures to automatically monitor applicable requirements of policies and procedures with regard to the following aspects:\n\n1. Configuration of system components to provide the cloud service within the cloud service provider's area of responsibility;\n2. Performance and availability of these system components;\n3. Response time to incidents and security incidents; and\n4. Recovery time (time to completion of error handling)."
   }
  }
 ]
}
