{
 "id": "https://ns.cyber.gov.au/ism/req/ism-1523",
 "version": "2026.06.18",
 "label": "ISM-1523",
 "lifecycle": "active",
 "title": "Control: ism-1523",
 "statements": [
  {
   "id": "smt",
   "modality": "unspecified",
   "obligated-parties": [
    "https://ns.cyber.gov.au/ism/party/organisation"
   ],
   "prose": {
    "en": "A sample of security-relevant events relating to data transfer policies are taken at least every three months and assessed against security policies for CDSs to identify any operational failures."
   }
  }
 ]
}
