{
 "id": "https://ns.bsi.bund.de/gspp/req/SENS.7.7",
 "version": "2026-07-16T05:11:52.605669+00:00",
 "label": "SENS.7.7",
 "lifecycle": "active",
 "title": "SPAM - Anhänge",
 "statements": [
  {
   "id": "smt",
   "modality": "should",
   "obligated-parties": [
    "https://ns.bsi.bund.de/gspp/party/institution"
   ],
   "prose": {
    "de": "Sensibilisierung für Nutzende von Interpersoneller Kommunikation SOLLTE gegen das Öffnen von Anhängen in SPAM sensibilisieren."
   }
  }
 ],
 "facets": {
  "https://ns.oscal.org/stdlib/facet/statement-grammar@1": {
   "by-statement": {
    "smt": {
     "action": "sensibilisieren",
     "result": "gegen das Öffnen von Anhängen in SPAM",
     "target-object-categories": [
      "Nutzende",
      "Interpersonelle Kommunikation"
     ]
    }
   }
  },
  "https://ns.oscal.org/stdlib/facet/assessment-criteria@1": {
   "by-statement": {
    "smt": {
     "required-documentation": [
      "Schulungsplan"
     ]
    }
   }
  },
  "https://ns.oscal.org/stdlib/facet/security-objectives@1": {
   "by-statement": {
    "smt": {
     "confidentiality": "1",
     "integrity": "1",
     "availability": "1",
     "authenticity": "0",
     "threat-refs": [
      "https://ns.bsi.bund.de/gspp/threat/G-0.18"
     ]
    }
   }
  },
  "https://ns.bsi.bund.de/facet/gspp-taxonomy@1": {
   "by-statement": {
    "smt": {
     "class": "BSI-Stand-der-Technik-Kernel-G0",
     "sec-level": "normal-SdT",
     "effort": 1
    }
   }
  },
  "https://ns.bsi.bund.de/facet/gspp-narrative@1": {
   "by-statement": {
    "smt": {
     "guidance": {
      "de": "Das Öffnens von Anhängen in unerwünschten oder verdächtigen Nachrichten könnte dazu führen, dass Schadsoftware in die Systeme einer Institution gelangt oder vertrauliche Informationen abfließen. Angreifer versuchen oft, ihre Opfer zum Öffnen von Dateien zu drängen und nutzen diese dann, um Schadprogramme auszuführen. Im Zweifelsfall ist es sinnvoll stattdessen sinnvoll, Rücksprache über andere, bereits bekannte Erreichbarkeiten (z.B. Telefonnummer, bekannter Link im Intranet) zu halten und die Echtheit der Nachricht zu verifizieren, oder über die Meldewege einen potenziellen Vorfall zu melden. Nützlich sind zudem kompakte Checklisten, die die wichtigsten Prüfkriterien vor dem Öffnen eines Anhangs aufführen, wie z. B. die Überprüfung der Absenderadresse, die Plausibilität des Inhalts und die Art der Datei."
     }
    }
   }
  }
 },
 "aliases": [
  {
   "scheme": "bsi-uuid",
   "value": "5003cefa-020f-445f-8e23-4add09f63a47"
  }
 ]
}
