{
 "id": "https://ns.bsi.bund.de/gspp/req/BER.4.6",
 "version": "2026-07-16T05:11:52.605669+00:00",
 "label": "BER.4.6",
 "lifecycle": "active",
 "title": "Systemfunktionen ohne Authentifizierung",
 "statements": [
  {
   "id": "smt",
   "modality": "should",
   "obligated-parties": [
    "https://ns.bsi.bund.de/gspp/party/institution"
   ],
   "prose": {
    "de": "Berechtigung für IT-Systeme SOLLTE Funktionen, auf die ohne vorherige Authentifizierung zugegriffen werden kann, dokumentieren."
   }
  }
 ],
 "facets": {
  "https://ns.oscal.org/stdlib/facet/statement-grammar@1": {
   "by-statement": {
    "smt": {
     "action": "dokumentieren",
     "result": "Funktionen, auf die ohne vorherige Authentifizierung zugegriffen werden kann,",
     "target-object-categories": [
      "IT-Systeme"
     ]
    }
   }
  },
  "https://ns.oscal.org/stdlib/facet/assessment-criteria@1": {
   "by-statement": {
    "smt": {
     "required-documentation": [
      "Systemdokumentation"
     ]
    }
   }
  },
  "https://ns.oscal.org/stdlib/facet/security-objectives@1": {
   "by-statement": {
    "smt": {
     "confidentiality": "1",
     "integrity": "1",
     "availability": "1",
     "authenticity": "2",
     "threat-refs": [
      "https://ns.bsi.bund.de/gspp/threat/G-0.36",
      "https://ns.bsi.bund.de/gspp/threat/G-0.30",
      "https://ns.bsi.bund.de/gspp/threat/G-0.32"
     ]
    }
   }
  },
  "https://ns.bsi.bund.de/facet/gspp-taxonomy@1": {
   "by-statement": {
    "smt": {
     "class": "BSI-Stand-der-Technik-Kernel-G0",
     "sec-level": "normal-SdT",
     "effort": 4
    }
   }
  },
  "https://ns.bsi.bund.de/facet/gspp-narrative@1": {
   "by-statement": {
    "smt": {
     "guidance": {
      "de": "Funktionen ohne Authentifizierung sind alle Zugriffsmöglichkeiten auf Schnittstellen oder Daten des Systems, für die keine Authentifizierung erforderlich ist. Hierzu gehören z. B. Sprachassistenten, offene Webserver-Ports oder das Einblenden von Inhalten aus Apps auf dem Sperrbildschirm, wodurch persönliche Nachrichten oder Logintoken für Unbefugte zugänglich sein könnten. Solche Funktionen sind häufige Einfallstore für Angriffe auf das System oder für Datenleaks. Daher ist es sinnvoll eine Übersicht dieser Funktionen zu führen, selbst wenn die Funktionen benötigt werden."
     }
    }
   }
  }
 },
 "aliases": [
  {
   "scheme": "bsi-uuid",
   "value": "bf5b5f6a-f525-45fc-b5a5-62379b3e6b2f"
  }
 ]
}
