{
 "id": "https://ns.bsi.bund.de/gspp/req/NOT.4.11",
 "version": "2026-07-16T05:11:52.605669+00:00",
 "label": "NOT.4.11",
 "lifecycle": "active",
 "title": "Datenträgerarchiv",
 "statements": [
  {
   "id": "smt",
   "modality": "should",
   "obligated-parties": [
    "https://ns.bsi.bund.de/gspp/party/institution"
   ],
   "prose": {
    "de": "Notfallplanung SOLLTE ein Datenträgerarchiv installieren."
   }
  }
 ],
 "facets": {
  "https://ns.oscal.org/stdlib/facet/statement-grammar@1": {
   "by-statement": {
    "smt": {
     "action": "installieren",
     "result": "ein Datenträgerarchiv"
    }
   }
  },
  "https://ns.oscal.org/stdlib/facet/assessment-criteria@1": {
   "by-statement": {
    "smt": {
     "required-documentation": [
      "Datensicherungskonzept"
     ]
    }
   }
  },
  "https://ns.oscal.org/stdlib/facet/security-objectives@1": {
   "by-statement": {
    "smt": {
     "confidentiality": "1",
     "integrity": "2",
     "availability": "1",
     "authenticity": "0",
     "threat-refs": [
      "https://ns.bsi.bund.de/gspp/threat/G-0.45",
      "https://ns.bsi.bund.de/gspp/threat/G-0.39"
     ]
    }
   }
  },
  "https://ns.bsi.bund.de/facet/gspp-taxonomy@1": {
   "by-statement": {
    "smt": {
     "class": "BSI-Stand-der-Technik-Kernel-G0",
     "sec-level": "normal-SdT",
     "effort": 4
    }
   }
  },
  "https://ns.bsi.bund.de/facet/gspp-narrative@1": {
   "by-statement": {
    "smt": {
     "guidance": {
      "de": "Datenträgerarchive sind verschlossene Räume, die dediziert zur langfristigen Aufbewahrung von Datenträgern bestimmt sind. Die Anforderung gilt auch dann als umgesetzt, wenn zusätzlich zur Datensicherung im Datenträgerarchiv auch noch Kopien existieren, die nicht im Datenträgerarchiv aufbewahrt werden.  Ein wesentlicher Mehrwert von Datenträgerarchiven ist die geschützte Aufbewahrung. Daher zählt ein Datenträgerarchiv nur dann als Mehrwert, wenn das Archiv sich auch in einem anderen Brandabschnitt befindet als die Originaldaten."
     }
    }
   }
  }
 },
 "aliases": [
  {
   "scheme": "bsi-uuid",
   "value": "a7779b58-de2c-4f8c-aedd-008bdffcc823"
  }
 ]
}
