{
 "id": "https://ns.bsi.bund.de/gspp/set/tax/konf",
 "version": "2026-07-16T05:11:52.605669+00:00",
 "lifecycle": "active",
 "title": "Konfiguration",
 "members": [
  {
   "ref": "https://ns.bsi.bund.de/gspp/set/tax/konf-1",
   "sequence": 6500
  },
  {
   "ref": "https://ns.bsi.bund.de/gspp/set/tax/konf-2",
   "sequence": 6600
  },
  {
   "ref": "https://ns.bsi.bund.de/gspp/set/tax/konf-3",
   "sequence": 6690
  },
  {
   "ref": "https://ns.bsi.bund.de/gspp/set/tax/konf-4",
   "sequence": 6750
  },
  {
   "ref": "https://ns.bsi.bund.de/gspp/set/tax/konf-5",
   "sequence": 6780
  },
  {
   "ref": "https://ns.bsi.bund.de/gspp/set/tax/konf-6",
   "sequence": 6950
  },
  {
   "ref": "https://ns.bsi.bund.de/gspp/set/tax/konf-7",
   "sequence": 7120
  },
  {
   "ref": "https://ns.bsi.bund.de/gspp/set/tax/konf-8",
   "sequence": 7150
  },
  {
   "ref": "https://ns.bsi.bund.de/gspp/set/tax/konf-9",
   "sequence": 7190
  },
  {
   "ref": "https://ns.bsi.bund.de/gspp/set/tax/konf-10",
   "sequence": 7250
  },
  {
   "ref": "https://ns.bsi.bund.de/gspp/set/tax/konf-11",
   "sequence": 7340
  },
  {
   "ref": "https://ns.bsi.bund.de/gspp/set/tax/konf-12",
   "sequence": 7490
  },
  {
   "ref": "https://ns.bsi.bund.de/gspp/set/tax/konf-13",
   "sequence": 7610
  },
  {
   "ref": "https://ns.bsi.bund.de/gspp/set/tax/konf-14",
   "sequence": 7670
  },
  {
   "ref": "https://ns.bsi.bund.de/gspp/set/tax/konf-15",
   "sequence": 7720
  }
 ],
 "label": "KONF",
 "facets": {
  "https://ns.bsi.bund.de/facet/gspp-narrative@1": {
   "description": {
    "de": "Die Praktik Konfiguration stellt sicher, dass IT-Komponenten – wie Anwendungen und IT-Systeme – gemäß den festgelegten Informationssicherheitsrichtlinien eingerichtet und kontinuierlich gepflegt werden, um Sicherheitslücken durch fehlerhafte oder unsichere Einstellungen zu vermeiden. Dies umfasst auch die nachvollziehbare Erstellung und Fortführung der Dokumentation."
   }
  }
 },
 "aliases": [
  {
   "scheme": "bsi-uuid",
   "value": "8e46d34c-5145-44f8-882e-790e2dcffa09"
  }
 ]
}
