{
 "id": "https://ns.ccb.belgium.be/cyfun/req/PR.IR-01.2",
 "version": "2025-12-12",
 "label": "PR.IR-01.2",
 "lifecycle": "active",
 "title": {
  "en": "Requirement PR.IR-01.2"
 },
 "statements": [
  {
   "id": "smt",
   "modality": "must",
   "obligated-parties": [
    "https://ns.ccb.belgium.be/cyfun/party/organisation"
   ],
   "prose": {
    "en": "To safeguard critical systems, organisations shall implement network segmentation and segregation aligned with trust boundaries and asset criticality, thereby limiting threat propagation and enforcing strict access control."
   }
  }
 ]
}
