{
 "id": "https://ns.cyber.gov.au/ism/req/ism-2109",
 "version": "2026.06.18",
 "label": "ISM-2109",
 "lifecycle": "active",
 "title": {
  "en": "Control: ism-2109"
 },
 "statements": [
  {
   "id": "smt",
   "modality": "unspecified",
   "obligated-parties": [
    "https://ns.cyber.gov.au/ism/party/organisation"
   ],
   "prose": {
    "en": "Pre-boot authentication using passwords, or managed network-based key release, is implemented for media containing encrypted system volumes."
   }
  }
 ]
}
