{
 "id": "https://ns.cyber.gov.au/ism/req/ism-1909",
 "version": "2026.06.18",
 "label": "ISM-1909",
 "lifecycle": "active",
 "title": {
  "en": "Control: ism-1909"
 },
 "statements": [
  {
   "id": "smt",
   "modality": "unspecified",
   "obligated-parties": [
    "https://ns.cyber.gov.au/ism/party/organisation"
   ],
   "prose": {
    "en": "In resolving vulnerabilities, root cause analysis is performed and, to the greatest extent possible, entire vulnerability classes are remediated."
   }
  }
 ]
}
