{
 "id": "https://ns.cyber.gov.au/ism/set/tax/guidelines-for-cyber-security-roles-chief-informatio-daca04c",
 "version": "2026.06.18",
 "lifecycle": "active",
 "title": {
  "en": "Communicating a cyber security vision and strategy"
 },
 "members": [
  {
   "ref": "https://ns.cyber.gov.au/ism/req/ism-0720",
   "sequence": 920
  }
 ],
 "facets": {
  "https://ns.oscal.org/compat/oscal-1x@1": {
   "group-parts": [
    {
     "group": "Communicating a cyber security vision and strategy",
     "name": "overview",
     "prose": {
      "en": "To assist in facilitating cyber security cultural change and awareness within their organisation, across their organisation’s cyber supply chain and among their organisation’s customers, the CISO should act as a cyber security leader and regularly communicate the cyber security vision and strategy for their organisation. In doing so, a cyber security communications strategy can be helpful in achieving this outcome. As part of this, communication styles and content should be tailored to different target audiences."
     }
    }
   ]
  }
 }
}
