{
 "id": "https://ns.cyber.gov.au/ism/set/tax/guidelines-for-physical-security-facilities-and-systems",
 "version": "2026.06.18",
 "lifecycle": "active",
 "title": {
  "en": "Facilities and systems"
 },
 "members": [
  {
   "ref": "https://ns.cyber.gov.au/ism/set/tax/guidelines-for-physical-security-facilities-and-syst-304546f",
   "sequence": 2350
  },
  {
   "ref": "https://ns.cyber.gov.au/ism/set/tax/guidelines-for-physical-security-facilities-and-syst-8918180",
   "sequence": 2420
  },
  {
   "ref": "https://ns.cyber.gov.au/ism/set/tax/guidelines-for-physical-security-facilities-and-syst-3b4c625",
   "sequence": 2440
  },
  {
   "ref": "https://ns.cyber.gov.au/ism/set/tax/guidelines-for-physical-security-facilities-and-syst-523364e",
   "sequence": 2480
  },
  {
   "ref": "https://ns.cyber.gov.au/ism/set/tax/guidelines-for-physical-security-facilities-and-syst-b1a3e36",
   "sequence": 2510
  },
  {
   "ref": "https://ns.cyber.gov.au/ism/set/tax/guidelines-for-physical-security-facilities-and-syst-6c14893",
   "sequence": 2550
  },
  {
   "ref": "https://ns.cyber.gov.au/ism/set/tax/guidelines-for-physical-security-facilities-and-syst-45d43e9",
   "sequence": 2570
  }
 ],
 "facets": {
  "https://ns.oscal.org/compat/oscal-1x@1": {
   "group-parts": [
    {
     "group": "Facilities and systems",
     "name": "overview",
     "prose": {
      "en": "# Further information\n\nFurther information on the certification and accreditation authorities for physical security can be found in the Department of Home Affairs’ [Protective Security Policy Framework](#92679127-f61d-486a-a93e-df2a26dfb07a).\n\nFurther information on the physical security requirements for specific security zones can be found in the Department of Home Affairs’ [Protective Security Policy Framework](#92679127-f61d-486a-a93e-df2a26dfb07a).\n\nFurther information on selecting security zones and security containers for the protection of information technology (IT) equipment can be found in the Department of Home Affairs’ [Protective Security Policy Framework](#92679127-f61d-486a-a93e-df2a26dfb07a).\n\nFurther information on emanation security considerations associated with usage of RF devices in SECRET and TOP SECRET areas can be found in the ‘Emanation security’ section of the [Guidelines for communications infrastructure](#4defa9a8-c5f5-4b39-8b0a-537f14d9d14d).\n\nFurther information on medical devices approved by the Therapeutic Goods Administration for diagnostic or therapeutic purposes can be found on the [Australian Register of Therapeutic Goods](#8edb7798-5d97-4811-a8ba-add3d5a123cf)."
     }
    }
   ]
  }
 }
}
