{
 "id": "https://ns.bsi.bund.de/gspp/req/BER.3.10",
 "version": "2026-07-16T05:11:52.605669+00:00",
 "label": "BER.3.10",
 "lifecycle": "active",
 "title": {
  "de": "Identität-Zugangskonto"
 },
 "statements": [
  {
   "id": "smt",
   "modality": "should",
   "obligated-parties": [
    "https://ns.bsi.bund.de/gspp/party/institution"
   ],
   "prose": {
    "de": "Berechtigung SOLLTE ein Zugangskonto zu genau einer Identität zuweisen."
   }
  }
 ],
 "facets": {
  "https://ns.oscal.org/stdlib/facet/statement-grammar@1": {
   "by-statement": {
    "smt": {
     "action": "zuweisen",
     "result": "ein Zugangskonto zu genau einer Identität"
    }
   }
  },
  "https://ns.oscal.org/stdlib/facet/assessment-criteria@1": {
   "by-statement": {
    "smt": {
     "required-documentation": [
      "IT-Betriebskonzept"
     ]
    }
   }
  },
  "https://ns.oscal.org/stdlib/facet/security-objectives@1": {
   "by-statement": {
    "smt": {
     "confidentiality": "1",
     "integrity": "1",
     "availability": "1",
     "authenticity": "1",
     "threat-refs": [
      "https://ns.bsi.bund.de/gspp/threat/G-0.36",
      "https://ns.bsi.bund.de/gspp/threat/G-0.30",
      "https://ns.bsi.bund.de/gspp/threat/G-0.32"
     ]
    }
   }
  },
  "https://ns.bsi.bund.de/facet/gspp-taxonomy@1": {
   "by-statement": {
    "smt": {
     "class": "BSI-Stand-der-Technik-Kernel-G0",
     "sec-level": "normal-SdT",
     "effort": 2
    }
   }
  },
  "https://ns.bsi.bund.de/facet/gspp-narrative@1": {
   "by-statement": {
    "smt": {
     "guidance": {
      "de": "Wenn ein Zugangskonto genau einer Identität zugewiesen ist erleichtert dies die Vergabe von Berechtigungen nach dem Need-to-know-Prinzip. Außerdem kann so bei einem Vorfall nachvollzogen werden, welche Person welche Befehle ausgeführt hat, z.B. mittels des Audit Logs. Anders herum können einer Identität auch mehrere Zugangskonten zugewiesen sein, z.B. ein normalen Nutzungskonto und ein Zugangskonto für die Systemadministration."
     }
    }
   }
  }
 },
 "aliases": [
  {
   "scheme": "bsi-uuid",
   "value": "3aee31a9-78e2-453e-8bce-d4212130dbf7"
  }
 ]
}
